Noh-3.0.0a2.dist-info/DESCRIPTION.rst
Noh-3.0.0a2.dist-info/METADATA
Noh-3.0.0a2.dist-info/RECORD
Noh-3.0.0a2.dist-info/WHEEL
Noh-3.0.0a2.dist-info/metadata.json
Noh-3.0.0a2.dist-info/top_level.txt
noh/__init__.py
noh/__version__.py
noh/core.py
