Metadata-Version: 2.0
Name: Noh
Version: 3.0.0a2
Summary: A circuit based platform for connecting and planning machine learning algorithms.
Home-page: https://github.com/ktnyt/Noh
Author: Kotone Itaya
Author-email: kotone@sfc.keio.ac.jp
License: MIT
Platform: UNKNOWN
Classifier: License :: OSI Approved :: MIT License
Classifier: Programming Language :: Python
Classifier: Programming Language :: Python :: 3
Classifier: Programming Language :: Python :: 3.6
Classifier: Programming Language :: Python :: Implementation :: CPython
Classifier: Programming Language :: Python :: Implementation :: PyPy
Requires-Python: >=3.6.0
Requires-Dist: nose
